<?xml version = '1.0' encoding = 'UTF-8'?>
<Diagram class="oracle.dbtools.crest.swingui.relational.DPVRelational" name="Relational_1" id="980B7A02-F478-9734-24F4-E2D5ABCEE063">
<createdBy>piero</createdBy>
<modifiedBy>piero</modifiedBy>
<createdTime>2023-01-26 12:53:42 UTC</createdTime>
<autoRoute>false</autoRoute>
<boxInbox>true</boxInbox>
<showLegend>false</showLegend>
<showLabels>false</showLabels>
<showRelAttributes>false</showRelAttributes>
<gridEnabled>false</gridEnabled>
<showGrid>false</showGrid>
<diagramColor>-1</diagramColor>
<display>false</display>
<notation>1</notation>
<objectViews>
<OView class="oracle.dbtools.crest.swingui.relational.TVTable" oid="01CAEA93-784F-6E4D-8454-3272AEFE5126" otype="Table" vid="75DBEB76-002A-5890-078F-BD1BD5271E11">
<hideElementsInCurrentOnly>false</hideElementsInCurrentOnly>
<bounds x="928" y="244" width="318" height="138"/>
</OView>
<OView class="oracle.dbtools.crest.swingui.relational.TVTable" oid="05C676A0-EBA3-B755-FDD7-392627C70A08" otype="Table" vid="858799ED-FA59-F60E-F209-8B950DC33440">
<hideElementsInCurrentOnly>false</hideElementsInCurrentOnly>
<bounds x="1326" y="33" width="379" height="128"/>
</OView>
<OView class="oracle.dbtools.crest.swingui.relational.TVTable" oid="18890966-F5C9-E5FA-A258-291F7D88377A" otype="Table" vid="DAFB31F2-DB6A-86AA-B3FD-F48DF4AD918F">
<hideElementsInCurrentOnly>false</hideElementsInCurrentOnly>
<bounds x="1384" y="243" width="273" height="164"/>
</OView>
<OView class="oracle.dbtools.crest.swingui.relational.TVTable" oid="1BDD9F71-082A-711E-4F90-4029FC117AA1" otype="Table" vid="A9484BD8-9C27-A01A-4449-079163000AEF">
<hideElementsInCurrentOnly>false</hideElementsInCurrentOnly>
<bounds x="282" y="506" width="307" height="137"/>
</OView>
<OView class="oracle.dbtools.crest.swingui.relational.TVTable" oid="7ECC5982-06C7-415D-9832-1ECC28EF8B16" otype="Table" vid="D94F3E95-76E2-376C-F3F2-E64809CDFA09">
<hideElementsInCurrentOnly>false</hideElementsInCurrentOnly>
<bounds x="608" y="427" width="320" height="186"/>
</OView>
<OView class="oracle.dbtools.crest.swingui.relational.TVTable" oid="8062AC40-A671-74F2-899A-35012F2D778A" otype="Table" vid="F83D6AFE-6B29-41B5-B872-9DD634B48B8A">
<hideElementsInCurrentOnly>false</hideElementsInCurrentOnly>
<bounds x="1427" y="527" width="197" height="78"/>
</OView>
<OView class="oracle.dbtools.crest.swingui.relational.TVTable" oid="8430765E-25E6-A56E-FA52-236381FC5DEF" otype="Table" vid="1D52C66C-BBCB-1964-4ED6-51962CF7077A">
<hideElementsInCurrentOnly>false</hideElementsInCurrentOnly>
<bounds x="599" y="205" width="298" height="154"/>
</OView>
<OView class="oracle.dbtools.crest.swingui.relational.TVTable" oid="889950B7-8DB5-C793-95D3-4D5726194C51" otype="Table" vid="525CD17B-611E-6264-4607-E5A420C66872">
<hideElementsInCurrentOnly>false</hideElementsInCurrentOnly>
<bounds x="912" y="17" width="342" height="163"/>
</OView>
<OView class="oracle.dbtools.crest.swingui.relational.TVTable" oid="9C03217A-AB87-D693-178D-25AEF58ED8CD" otype="Table" vid="C4175173-BB91-1967-C74F-2F4BA6851369">
<hideElementsInCurrentOnly>false</hideElementsInCurrentOnly>
<bounds x="32" y="107" width="153" height="109"/>
</OView>
<OView class="oracle.dbtools.crest.swingui.relational.TVTable" oid="AE156DD0-0F6D-EB37-EEB2-856A1DBBB720" otype="Table" vid="BCD2AB7D-CFB1-1DB7-B1F4-87C77E6461E8">
<hideElementsInCurrentOnly>false</hideElementsInCurrentOnly>
<bounds x="113" y="399" width="171" height="94"/>
</OView>
<OView class="oracle.dbtools.crest.swingui.relational.TVTable" oid="FB54C56F-D7CD-62CB-629B-A72136FD8711" otype="Table" vid="80A83BB6-7430-42FE-36CB-EEA9B243C936">
<hideElementsInCurrentOnly>false</hideElementsInCurrentOnly>
<bounds x="255" y="113" width="326" height="158"/>
</OView>
</objectViews>
<connectors>
<Connector class="oracle.dbtools.crest.swingui.relational.TVFKRelation" oid="2C54587E-A082-6CFF-08EC-BBC971DC4349" otype="FKIndexAssociation" vid_source="1D52C66C-BBCB-1964-4ED6-51962CF7077A" vid_target="D94F3E95-76E2-376C-F3F2-E64809CDFA09">
<hideElementsInCurrentOnly>false</hideElementsInCurrentOnly>
<backgroundColor>-16777216</backgroundColor>
<lineWidth>1</lineWidth>
<points>
<point x="767" y="359"/>
<point x="767" y="427"/>
</points>
</Connector>
<Connector class="oracle.dbtools.crest.swingui.relational.TVFKRelation" oid="3F8B5E18-7D66-0BF4-60F0-02F29415DDD0" otype="FKIndexAssociation" vid_source="DAFB31F2-DB6A-86AA-B3FD-F48DF4AD918F" vid_target="75DBEB76-002A-5890-078F-BD1BD5271E11">
<hideElementsInCurrentOnly>false</hideElementsInCurrentOnly>
<backgroundColor>-16777216</backgroundColor>
<lineWidth>1</lineWidth>
<points>
<point x="1384" y="313"/>
<point x="1246" y="313"/>
</points>
</Connector>
<Connector class="oracle.dbtools.crest.swingui.relational.TVFKRelation" oid="47E57EDE-2779-5BD0-6B19-FAF99D43826E" otype="FKIndexAssociation" vid_source="C4175173-BB91-1967-C74F-2F4BA6851369" vid_target="C4175173-BB91-1967-C74F-2F4BA6851369">
<hideElementsInCurrentOnly>false</hideElementsInCurrentOnly>
<backgroundColor>-16777216</backgroundColor>
<lineWidth>1</lineWidth>
<points>
<point x="32" y="173"/>
<point x="12" y="173"/>
<point x="13" y="239"/>
<point x="85" y="238"/>
<point x="85" y="216"/>
</points>
</Connector>
<Connector class="oracle.dbtools.crest.swingui.relational.TVFKRelation" oid="491EE1F4-F302-CD2C-2DB2-A7567524DACE" otype="FKIndexAssociation" vid_source="80A83BB6-7430-42FE-36CB-EEA9B243C936" vid_target="A9484BD8-9C27-A01A-4449-079163000AEF">
<hideElementsInCurrentOnly>false</hideElementsInCurrentOnly>
<backgroundColor>-16777216</backgroundColor>
<lineWidth>1</lineWidth>
<points>
<point x="431" y="271"/>
<point x="431" y="506"/>
</points>
</Connector>
<Connector class="oracle.dbtools.crest.swingui.relational.TVFKRelation" oid="5041377C-81D4-F94C-E7C0-889561607339" otype="FKIndexAssociation" vid_source="F83D6AFE-6B29-41B5-B872-9DD634B48B8A" vid_target="DAFB31F2-DB6A-86AA-B3FD-F48DF4AD918F">
<hideElementsInCurrentOnly>false</hideElementsInCurrentOnly>
<backgroundColor>-16777216</backgroundColor>
<lineWidth>1</lineWidth>
<points>
<point x="1525" y="527"/>
<point x="1525" y="407"/>
</points>
</Connector>
<Connector class="oracle.dbtools.crest.swingui.relational.TVFKRelation" oid="51E25F91-9322-BF42-3CD4-54081E96D1B5" otype="FKIndexAssociation" vid_source="80A83BB6-7430-42FE-36CB-EEA9B243C936" vid_target="BCD2AB7D-CFB1-1DB7-B1F4-87C77E6461E8">
<hideElementsInCurrentOnly>false</hideElementsInCurrentOnly>
<backgroundColor>-16777216</backgroundColor>
<lineWidth>1</lineWidth>
<points>
<point x="269" y="271"/>
<point x="269" y="399"/>
</points>
</Connector>
<Connector class="oracle.dbtools.crest.swingui.relational.TVFKRelation" oid="5F08CF35-5B3A-98F8-5B72-E551FBF09FEC" otype="FKIndexAssociation" vid_source="D94F3E95-76E2-376C-F3F2-E64809CDFA09" vid_target="1D52C66C-BBCB-1964-4ED6-51962CF7077A">
<hideElementsInCurrentOnly>false</hideElementsInCurrentOnly>
<backgroundColor>-16777216</backgroundColor>
<lineWidth>1</lineWidth>
<points>
<point x="767" y="427"/>
<point x="767" y="359"/>
</points>
</Connector>
<Connector class="oracle.dbtools.crest.swingui.relational.TVFKRelation" oid="6472B9FA-E195-D847-4675-D56A10FC3413" otype="FKIndexAssociation" vid_source="C4175173-BB91-1967-C74F-2F4BA6851369" vid_target="80A83BB6-7430-42FE-36CB-EEA9B243C936">
<hideElementsInCurrentOnly>false</hideElementsInCurrentOnly>
<backgroundColor>-16777216</backgroundColor>
<lineWidth>1</lineWidth>
<points>
<point x="185" y="179"/>
<point x="255" y="179"/>
</points>
</Connector>
<Connector class="oracle.dbtools.crest.swingui.relational.TVFKRelation" oid="8ECC7E01-08E9-149E-561C-6DF2B564289A" otype="FKIndexAssociation" vid_source="525CD17B-611E-6264-4607-E5A420C66872" vid_target="75DBEB76-002A-5890-078F-BD1BD5271E11">
<hideElementsInCurrentOnly>false</hideElementsInCurrentOnly>
<backgroundColor>-16777216</backgroundColor>
<lineWidth>1</lineWidth>
<points>
<point x="1087" y="180"/>
<point x="1087" y="244"/>
</points>
</Connector>
<Connector class="oracle.dbtools.crest.swingui.relational.TVFKRelation" oid="90E49EC9-3A67-A76B-D598-2591506D47CD" otype="FKIndexAssociation" vid_source="80A83BB6-7430-42FE-36CB-EEA9B243C936" vid_target="525CD17B-611E-6264-4607-E5A420C66872">
<hideElementsInCurrentOnly>false</hideElementsInCurrentOnly>
<backgroundColor>-16777216</backgroundColor>
<lineWidth>1</lineWidth>
<points>
<point x="581" y="146"/>
<point x="912" y="146"/>
</points>
</Connector>
<Connector class="oracle.dbtools.crest.swingui.relational.TVFKRelation" oid="ADB4C350-C57F-7935-5CC6-5D815B44CD45" otype="FKIndexAssociation" vid_source="C4175173-BB91-1967-C74F-2F4BA6851369" vid_target="BCD2AB7D-CFB1-1DB7-B1F4-87C77E6461E8">
<hideElementsInCurrentOnly>false</hideElementsInCurrentOnly>
<backgroundColor>-16777216</backgroundColor>
<lineWidth>1</lineWidth>
<points>
<point x="134" y="216"/>
<point x="134" y="399"/>
</points>
</Connector>
<Connector class="oracle.dbtools.crest.swingui.relational.TVFKRelation" oid="DE80876F-296A-CDF2-EA0E-3F49E38BE4DF" otype="FKIndexAssociation" vid_source="80A83BB6-7430-42FE-36CB-EEA9B243C936" vid_target="D94F3E95-76E2-376C-F3F2-E64809CDFA09">
<hideElementsInCurrentOnly>false</hideElementsInCurrentOnly>
<backgroundColor>-16777216</backgroundColor>
<lineWidth>1</lineWidth>
<points>
<point x="500" y="271"/>
<point x="500" y="436"/>
<point x="608" y="436"/>
</points>
</Connector>
<Connector class="oracle.dbtools.crest.swingui.relational.TVFKRelation" oid="F147460E-AD40-B5C7-672E-99FBB0FA50A0" otype="FKIndexAssociation" vid_source="DAFB31F2-DB6A-86AA-B3FD-F48DF4AD918F" vid_target="858799ED-FA59-F60E-F209-8B950DC33440">
<hideElementsInCurrentOnly>false</hideElementsInCurrentOnly>
<backgroundColor>-16777216</backgroundColor>
<lineWidth>1</lineWidth>
<points>
<point x="1520" y="243"/>
<point x="1520" y="161"/>
</points>
</Connector>
</connectors>
<arcs>
<Arc class="oracle.dbtools.crest.swingui.relational.TVFKArc" oid="E8895F91-CC98-29EE-94FC-A581323C5E07" otype="FKArc" vid="0A24C2DE-87ED-7C63-8F4A-309AA2CCD960">
<hideElementsInCurrentOnly>false</hideElementsInCurrentOnly>
<bounds x="235" y="93" width="366" height="198"/>
</Arc>
</arcs>
</Diagram>